<?xml version="1.0" encoding="utf-8"?>
<LanguageData>
  <!-- EN: Switches nutrient paste flow on/off. -->
  <VNPE_NutValve>Вкл./выкл. подачу питательной пасты.</VNPE_NutValve>
  <!-- EN: Switches nutrient paste flow on/off. A pawn will come open/close the valve. -->
  <VNPE_NutValveDesc>Дать команду включения или отключения подачи питательной пасты. Вскоре поселенец подойдёт и переключит выключатель.</VNPE_NutValveDesc>

  <!-- EN: Drain vat -->
  <VNPE_Drain>Опустошить бак</VNPE_Drain>
  <!-- EN: Drain vat content. This will remove any unwanted ingredients from the vat. -->
  <VNPE_DrainDesc>Слить содержимое бака. Это удалит из него все нежелательные ингредиенты.</VNPE_DrainDesc>

  <!-- EN: Extract 5 meals -->
  <VNPE_Extract5>Извлечь 5 порций</VNPE_Extract5>
  <!-- EN: Extract 10 meals -->
  <VNPE_Extract10>Извлечь 10 порций</VNPE_Extract10>
  <!-- EN: Extract 20 meals -->
  <VNPE_Extract20>Извлечь 20 порций</VNPE_Extract20>
</LanguageData>