<?xml version="1.0" encoding="utf-8"?>
<LanguageData>

  <!-- SPECIAL: These Recipes from makeable ThingDefs (which include <recipeMaker>), generated by RimTrans -->


  <!-- Recipe Users: DryadCircle -->

  <Make_DryadOrgan.label>создать орган дриады</Make_DryadOrgan.label>
  <Make_DryadOrgan.description>Создать орган дриады.</Make_DryadOrgan.description>
  <Make_DryadOrgan.jobString>Making dryad organ.</Make_DryadOrgan.jobString>

  <Make_DryadicOrgan.label>создать орган дриады</Make_DryadicOrgan.label>
  <Make_DryadicOrgan.description>Создать орган дриады.</Make_DryadicOrgan.description>
  <Make_DryadicOrgan.jobString>Making dryadic organ.</Make_DryadicOrgan.jobString>

  <Make_DryadicHeart.label>создать сердце дриады</Make_DryadicHeart.label>
  <Make_DryadicHeart.description>Создать сердце дриады.</Make_DryadicHeart.description>
  <Make_DryadicHeart.jobString>Making dryadic heart.</Make_DryadicHeart.jobString>

  <Make_DryadicLung.label>создать легкое дриады</Make_DryadicLung.label>
  <Make_DryadicLung.description>Создать легкое дриады.</Make_DryadicLung.description>
  <Make_DryadicLung.jobString>Making dryadic lung.</Make_DryadicLung.jobString>

  <Make_DryadicLiver.label>создать печень дриады</Make_DryadicLiver.label>
  <Make_DryadicLiver.description>Создать печень дриады.</Make_DryadicLiver.description>
  <Make_DryadicLiver.jobString>Making dryadic liver.</Make_DryadicLiver.jobString>


  <!-- Recipe Users: DryadCircle, DryadCircle -->

  <Make_DryadicKidney.label>создать почку дриады</Make_DryadicKidney.label>
  <Make_DryadicKidney.description>Создать почку дриады.</Make_DryadicKidney.description>
  <Make_DryadicKidney.jobString>Making dryadic kidney.</Make_DryadicKidney.jobString>


  <!-- Recipe Users: DryadCircle -->

  <Make_DryadicEye.label>создать глаз дриады</Make_DryadicEye.label>
  <Make_DryadicEye.description>Создать глаз дриады.</Make_DryadicEye.description>
  <Make_DryadicEye.jobString>Making dryadic eye.</Make_DryadicEye.jobString>

  <Make_DryadicNose.label>создать нос дриады</Make_DryadicNose.label>
  <Make_DryadicNose.description>Создать нос дриады.</Make_DryadicNose.description>
  <Make_DryadicNose.jobString>Making dryadic nose.</Make_DryadicNose.jobString>

  <Make_DryadicEar.label>создать ухо дриады</Make_DryadicEar.label>
  <Make_DryadicEar.description>Создать ухо дриады.</Make_DryadicEar.description>
  <Make_DryadicEar.jobString>Making dryadic ear.</Make_DryadicEar.jobString>

  <Make_DryadicHand.label>создать кисть дриады</Make_DryadicHand.label>
  <Make_DryadicHand.description>Создать кисть дриады.</Make_DryadicHand.description>
  <Make_DryadicHand.jobString>Making dryadic hand.</Make_DryadicHand.jobString>

  <Make_DryadicFoot.label>создать стопу дриады</Make_DryadicFoot.label>
  <Make_DryadicFoot.description>Создать стопу дриады.</Make_DryadicFoot.description>
  <Make_DryadicFoot.jobString>Making dryadic foot.</Make_DryadicFoot.jobString>

  <Make_DryadLeg.label>создать ногу дриады</Make_DryadLeg.label>
  <Make_DryadLeg.description>Создать ногу дриады.</Make_DryadLeg.description>
  <Make_DryadLeg.jobString>Making dryad leg.</Make_DryadLeg.jobString>

  <Make_DryadArm.label>создать руку дриады</Make_DryadArm.label>
  <Make_DryadArm.description>Создать руку дриады.</Make_DryadArm.description>
  <Make_DryadArm.jobString>Making dryad arm.</Make_DryadArm.jobString>


  <!-- Recipe Users: DryadSculptureSpot -->

  <Make_DryadSculptureSmall.label>изготовить небольшую дриадскую скульптуру</Make_DryadSculptureSmall.label>
  <Make_DryadSculptureSmall.description>Изготовить небольшую дриадскую скульптуру.</Make_DryadSculptureSmall.description>
  <Make_DryadSculptureSmall.jobString>Making small dryadic sculpture.</Make_DryadSculptureSmall.jobString>

  <Make_DryadSculptureLarge.label>изготовить большую дриадскую скульптуру</Make_DryadSculptureLarge.label>
  <Make_DryadSculptureLarge.description>Изготовить большую дриадскую скульптуру.</Make_DryadSculptureLarge.description>
  <Make_DryadSculptureLarge.jobString>Making large dryadic sculpture.</Make_DryadSculptureLarge.jobString>

  <Make_DryadMassiveStatue.label>изготовить огромную дриадскую скульптуру</Make_DryadMassiveStatue.label>
  <Make_DryadMassiveStatue.description>Изготовить огромную дриадскую скульптуру.</Make_DryadMassiveStatue.description>
  <Make_DryadMassiveStatue.jobString>Making massive dryadic statue.</Make_DryadMassiveStatue.jobString>

  <Make_DryadPillarLarge.label>изготовить большой дриадский столб</Make_DryadPillarLarge.label>
  <Make_DryadPillarLarge.description>Изготовить большой дриадский столб.</Make_DryadPillarLarge.description>
  <Make_DryadPillarLarge.jobString>Making large dryadic pillar.</Make_DryadPillarLarge.jobString>


  <!-- Recipe Users: DryadFurnitureSpot -->

  <Make_DryadBasin.label>сделать декоративную чашу</Make_DryadBasin.label>
  <Make_DryadBasin.description>Сделать декоративную чашу.</Make_DryadBasin.description>
  <Make_DryadBasin.jobString>Making decorative basin.</Make_DryadBasin.jobString>

  <Make_DryadTable.label>сделать декоративный стол</Make_DryadTable.label>
  <Make_DryadTable.description>Сделать декоративный стол.</Make_DryadTable.description>
  <Make_DryadTable.jobString>Making decorative table.</Make_DryadTable.jobString>

  <Make_DryadStool.label>сделать декоративный стул</Make_DryadStool.label>
  <Make_DryadStool.description>Сделать декоративный стул.</Make_DryadStool.description>
  <Make_DryadStool.jobString>Making decorative stool.</Make_DryadStool.jobString>

  <Make_DryadOrbStand.label>сделать декоративную статую</Make_DryadOrbStand.label>
  <Make_DryadOrbStand.description>Сделать декоративную статую.</Make_DryadOrbStand.description>
  <Make_DryadOrbStand.jobString>Making decorative stand.</Make_DryadOrbStand.jobString>


  <!-- Recipe Users: DryadCircle -->

  <Make_DryadHusk.label>создать оболочку дриады</Make_DryadHusk.label>
  <Make_DryadHusk.description>Создать оболочку дриады.</Make_DryadHusk.description>
  <Make_DryadHusk.jobString>Making dryad husk.</Make_DryadHusk.jobString>

  <Make_DryadBody.label>создать тело дриады 1</Make_DryadBody.label>
  <Make_DryadBody.description>Создать тело дриады.</Make_DryadBody.description>
  <Make_DryadBody.jobString>Making dryad body.</Make_DryadBody.jobString>

  <Make_DryadicBody.label>создать тело дриады 2</Make_DryadicBody.label>
  <Make_DryadicBody.description>Создать тело дриады.</Make_DryadicBody.description>
  <Make_DryadicBody.jobString>Making dryadic body.</Make_DryadicBody.jobString>


  <!-- Recipe Users: DryadSculptureSpot -->

  <Make_Apparel_DryadicMask.label>создать маску дриады</Make_Apparel_DryadicMask.label>
  <Make_Apparel_DryadicMask.description>Создать маску дриады.</Make_Apparel_DryadicMask.description>
  <Make_Apparel_DryadicMask.jobString>Making dryadic mask.</Make_Apparel_DryadicMask.jobString>


  <!-- Recipe Users: DryadCircle -->

  <Make_MeleeWeapon_SylScythe.label>создать косу дриады</Make_MeleeWeapon_SylScythe.label>
  <Make_MeleeWeapon_SylScythe.description>Создать косу дриады.</Make_MeleeWeapon_SylScythe.description>
  <Make_MeleeWeapon_SylScythe.jobString>Making dryadic scythe.</Make_MeleeWeapon_SylScythe.jobString>


</LanguageData>