<?xml version="1.0" encoding="utf-8"?>
<LanguageData>

  <!-- Mental breaks: extreme -->

  <TM_Berserk.label>Берсерк</TM_Berserk.label>
  <TM_Berserk.recoveryMessage>У {0} ярость берсерка подошла к концу.</TM_Berserk.recoveryMessage>
  <TM_Berserk.baseInspectLine>Психическое состояние: Берсерк</TM_Berserk.baseInspectLine>

  <TM_PanicFlee.label>паническое бегство</TM_PanicFlee.label>
  <TM_PanicFlee.baseInspectLine>Психическое состояние: панический бег</TM_PanicFlee.baseInspectLine>


  <!-- <MentalBreakDef>
    <defName>TM_WanderPsychotic</defName>
    <mentalState>TM_WanderPsychotic</mentalState>
    <baseCommonality>.1</baseCommonality>
    <intensity>Major</intensity>
  </MentalBreakDef> -->

  <TM_WanderPsychotic.label>блуждание в психозе</TM_WanderPsychotic.label>
  <TM_WanderPsychotic.recoveryMessage>{0} больше не блуждает в психотическом состоянии.</TM_WanderPsychotic.recoveryMessage>
  <TM_WanderPsychotic.baseInspectLine>Психическое состояние: блуждание в психозе</TM_WanderPsychotic.baseInspectLine>


  <!-- <MentalBreakDef>
    <defName>TM_WanderSad</defName>
    <mentalState>TM_WanderSad</mentalState>
    <baseCommonality>0.15</baseCommonality>
    <intensity>Minor</intensity>
  </MentalBreakDef> -->

  <TM_WanderSad.label>грустно бродит</TM_WanderSad.label>
  <TM_WanderSad.recoveryMessage>{0} больше не блуждает в печали.</TM_WanderSad.recoveryMessage>
  <TM_WanderSad.baseInspectLine>Психическое состояние: грустно бродит</TM_WanderSad.baseInspectLine>


  <!-- <MentalBreakDef>
    <defName>TM_WanderConfused</defName>
    <mentalState>TM_WanderConfused</mentalState>
    <baseCommonality>0.0</baseCommonality>
    <intensity>Minor</intensity>
  </MentalBreakDef> -->

  <TM_WanderConfused.label>растерянно бродит</TM_WanderConfused.label>
  <TM_WanderConfused.recoveryMessage>{0} больше не смущен.</TM_WanderConfused.recoveryMessage>
  <TM_WanderConfused.baseInspectLine>Психическое состояние: растерянно бродит</TM_WanderConfused.baseInspectLine>


</LanguageData>