<?xml version="1.0" encoding="utf-8" ?>
<Defs>

    <RecipeDef Class="UniversalFermenterSK.RecipeDef_UF">
		<defName>Make_Mead_AB</defName>
		<label>make mead</label>
		<description>Make mead from must. Takes 6 days to make.</description>
		<ingredients>
			<li>
				<filter>
					<thingDefs>
						<li>RB_Must</li>
					</thingDefs>
				</filter>
				<count>20</count>
			</li>
		</ingredients>
		<products>
			<RB_Mead>20</RB_Mead>
		</products>
		<recipeUsers>
			<li>UniversalFermenter</li>
		</recipeUsers>
		<!-- RecipeDef_UF fields -->
		<usesTemperature>true</usesTemperature>
		<temperatureSafe>0.0~33.0</temperatureSafe>
		<temperatureIdeal>7.0~30.0</temperatureIdeal>
		<ruinedPerDegreePerHour>2.5</ruinedPerDegreePerHour>
		<!-- percent per degree per hour -->
		<speedBelowSafe>0.1</speedBelowSafe>
		<speedAboveSafe>1.0</speedAboveSafe>
		<processDays>6</processDays>
		<!-- in days, 60000 ticks is a day -->
		<sunFactor>1.0~1.0</sunFactor>
		<rainFactor>1.0~1.0</rainFactor>
		<snowFactor>1.0~1.0</snowFactor>
		<windFactor>1.0~1.0</windFactor>
		<qualityDays>(4, 5, 6, 7, 8, 9, 10)</qualityDays>
		<graphicSuffix/>
	</RecipeDef>
	
</Defs>